iksemel.pypy310-pp73-x86_64-linux-gnu.so
iksemel-1.6.2.dist-info/COPYING
iksemel-1.6.2.dist-info/top_level.txt
iksemel-1.6.2.dist-info/WHEEL
iksemel-1.6.2.dist-info/METADATA
iksemel-1.6.2.dist-info/AUTHORS
iksemel-1.6.2.dist-info/RECORD
