Metadata-Version: 2.1
Name: iksemel
Version: 1.6.2
Summary: This is an XML parser library mainly designed for Jabber applications.
Author-email: Suleyman Poyraz <zaryob.dev@gmail.com>
Project-URL: Homepage, https://github.com/Zaryob/iksemel
Project-URL: Bug Tracker, https://github.com/Zaryob/iksemel/issues
Classifier: Programming Language :: Python :: 3
Classifier: License :: OSI Approved :: GNU Lesser General Public License v2 or later (LGPLv2+)
Classifier: Operating System :: OS Independent
Requires-Python: >=3.7
License-File: COPYING
License-File: AUTHORS
